MANIFEST.in
README.md
requirements-extras.txt
requirements.txt
setup.py
bin/rhdzmota
src/rhdzmota/VERSION
src/rhdzmota/__main__.py
src/rhdzmota/celery.py
src/rhdzmota/settings.py
src/rhdzmota.egg-info/PKG-INFO
src/rhdzmota.egg-info/SOURCES.txt
src/rhdzmota.egg-info/dependency_links.txt
src/rhdzmota.egg-info/entry_points.txt
src/rhdzmota.egg-info/requires.txt
src/rhdzmota.egg-info/top_level.txt
src/rhdzmota/celery_workers/__init__.py
src/rhdzmota/celery_workers/hello.py
src/rhdzmota/cli/__init__.py
src/rhdzmota/google_services/__init__.py
src/rhdzmota/google_services/auth.py
src/rhdzmota/google_services/gmail.py
src/rhdzmota/heartbeat/__init__.py
src/rhdzmota/heartbeat/daemon.py
src/rhdzmota/heartbeat/daemon_heart.py
src/rhdzmota/interface/__init__.py
src/rhdzmota/interface/cli.py
src/rhdzmota/iso3166/__init__.py
src/rhdzmota/iso3166/country_codes.py
src/rhdzmota/iso3166/datafiles/countries.json
src/rhdzmota/iso3166/datafiles/default.json
src/rhdzmota/iso3166/datafiles/mx.json
src/rhdzmota/iso3166/datafiles/us.json
src/rhdzmota/mail/__init__.py
src/rhdzmota/mail/message.py
src/rhdzmota/mail/server.py
src/rhdzmota/utils/__init__.py
src/rhdzmota/utils/gists.py
src/rhdzmota/utils/json_web_token.py
src/rhdzmota/utils/misc.py
src/rhdzmota/utils/rsa_encryption.py
src/rhdzmota/utils/runtime.py
src/rhdzmota/wrappers/__init__.py
src/rhdzmota/wrappers/_streamlit/__init__.py
src/rhdzmota/wrappers/_streamlit/cli.py
src/rhdzmota/wrappers/_streamlit/example_views.py