Metadata-Version: 2.1
Name: rhdzmota
Version: 2.7.0
Summary: RHDZMOTA Package
Home-page: https://github.com/rhdzmota/package.rhdzmota.com
Author: Rodrigo H. Mota
Author-email: info@rhdzmota.com
Requires-Python: >=3.8.10
Provides-Extra: default
Provides-Extra: all
Provides-Extra: develop
Provides-Extra: celery
Provides-Extra: google_services
Provides-Extra: backend
Provides-Extra: frontend
Provides-Extra: tools
